gamtools/__init__.py
gamtools/call_windows.py
gamtools/compaction.py
gamtools/cosegregation.py
gamtools/cosegregation_internal.c
gamtools/cosegregation_internal.pyx
gamtools/cosegregation_internal.so
gamtools/count_tables.py
gamtools/enrichment.py
gamtools/main.py
gamtools/matrix.py
gamtools/permutation.py
gamtools/pipeline.py
gamtools/plotting.py
gamtools/radial_position.py
gamtools/segregation.py
gamtools/select_samples.py
gamtools/utils.py
gamtools/data/examples/qc_parameters.example.cfg
gamtools/data/scripts/mapping_stats.sh
gamtools/qc/__init__.py
gamtools/qc/fastqc.py
gamtools/qc/merge.py
gamtools/qc/pass_qc.py
gamtools/qc/screen.py
gamtools/qc/segregation.py
gamtools/tests/test_call_windows.py
gamtools/tests/test_cosegregation.py
gamtools/tests/test_dependencies.py
gamtools/tests/test_gamtools.py
gamtools/tests/test_installation.py
gamtools/tests/test_matrix.py
gamtools/tests/test_parser.py
gamtools/tests/test_permutation.py
gamtools/tests/test_segregation.py
gamtools-1.1.0.dist-info/DESCRIPTION.rst
gamtools-1.1.0.dist-info/METADATA
gamtools-1.1.0.dist-info/RECORD
gamtools-1.1.0.dist-info/WHEEL
gamtools-1.1.0.dist-info/entry_points.txt
gamtools-1.1.0.dist-info/metadata.json
gamtools-1.1.0.dist-info/top_level.txt
