Metadata-Version: 1.1
Name: gamtools
Version: 1.1.0
Summary: A package containing some utilities for analyzing GAM data.
Home-page: http://gam.tools
Author: Rob Beagrie
Author-email: rob@beagrie.com
License: Apache2.0
Platform: UNKNOWN
Classifier: Development Status :: 5 - Production/Stable
Classifier: Intended Audience :: Science/Research
Classifier: Topic :: Scientific/Engineering :: Bio-Informatics
Classifier: License :: OSI Approved :: Apache Software License
